brain_games/__init__.py
brain_games/cli.py
brain_games/engine.py
brain_games/games/__init__.py
brain_games/games/calc.py
brain_games/games/even.py
brain_games/games/gcd.py
brain_games/games/prime.py
brain_games/games/progression.py
brain_games/scripts/__init__.py
brain_games/scripts/brain_calc.py
brain_games/scripts/brain_even.py
brain_games/scripts/brain_games.py
brain_games/scripts/brain_gcd.py
brain_games/scripts/brain_prime.py
brain_games/scripts/brain_progression.py
brain_games-0.5.1.dist-info/entry_points.txt
brain_games-0.5.1.dist-info/LICENSE
brain_games-0.5.1.dist-info/WHEEL
brain_games-0.5.1.dist-info/METADATA
brain_games-0.5.1.dist-info/RECORD
