Metadata-Version: 2.1
Name: brain-games
Version: 0.5.1
Summary: first of four training projects
Home-page: https://github.com/ilitili/python-project-lvl1
License: MIT
Author: ilitili
Author-email: momcoveylebozo@gmail.com
Requires-Python: >=3.8,<4.0
Classifier: Development Status :: 5 - Production/Stable
Classifier: Intended Audience :: Education
Classifier: License :: OSI Approved :: MIT License
Classifier: Natural Language :: English
Classifier: Programming Language :: Python :: 3
Classifier: Programming Language :: Python :: 3.10
Classifier: Programming Language :: Python :: 3.8
Classifier: Programming Language :: Python :: 3.9
Classifier: Topic :: Education
Requires-Dist: prompt (>=0.4.1,<0.5.0)
Requires-Dist: pyprimer (>=0.1.0,<0.2.0)
Project-URL: Repository, https://github.com/ilitili/python-project-lvl1
